{"format":2,"version":"5.3.1","globals":"ef6232a9599d1e2b96edf62b270f8ffe","files":{"goals___init___py":{"hash":"af9d0d0de0ea3b71d198bc63f1499a7d","index":{"nums":[1,0,0,0,0,0,0],"html_filename":"goals___init___py.html","relative_filename":"goals/__init__.py"}},"goals_admin_py":{"hash":"e96e854f1da0d973f3cd701b5b043b48","index":{"nums":[1,9,0,0,0,0,0],"html_filename":"goals_admin_py.html","relative_filename":"goals/admin.py"}},"goals_forms_py":{"hash":"ae858498e7cbe71c6da5fa147e663735","index":{"nums":[1,16,0,0,0,0,0],"html_filename":"goals_forms_py.html","relative_filename":"goals/forms.py"}},"goals_models_py":{"hash":"47481dd00420ee145617bdd5b6810892","index":{"nums":[1,17,0,0,0,0,0],"html_filename":"goals_models_py.html","relative_filename":"goals/models.py"}},"goals_signals_py":{"hash":"0ed95637d372f62694f41b06d8b5ecbb","index":{"nums":[1,8,0,0,0,0,0],"html_filename":"goals_signals_py.html","relative_filename":"goals/signals.py"}},"goals_urls_py":{"hash":"026565381092867c0e8c27a8d4cac3a2","index":{"nums":[1,4,0,0,0,0,0],"html_filename":"goals_urls_py.html","relative_filename":"goals/urls.py"}},"goals_views_py":{"hash":"ad81534bd27e86d6ec10aac22abeff0e","index":{"nums":[1,138,0,14,0,0,0],"html_filename":"goals_views_py.html","relative_filename":"goals/views.py"}}}}